pconst/__init__.py
pconst/const.py
pconst-1.1.2.dist-info/LICENSE
pconst-1.1.2.dist-info/METADATA
pconst-1.1.2.dist-info/WHEEL
pconst-1.1.2.dist-info/top_level.txt
pconst-1.1.2.dist-info/RECORD
